{
    "parent":  "minecraft:item/generated",
    "textures":  {
                     "layer0":  "stardewcraft:item/animal_product/large_brown_egg",
                     "particle":  "stardewcraft:item/animal_product/large_brown_egg"
                 },
    "overrides":  [
                      {
                          "predicate":  {
                                            "custom_model_data":  1
                                        },
                          "model":  "stardewcraft:item/large_egg_brown_silver"
                      },
                      {
                          "predicate":  {
                                            "custom_model_data":  2
                                        },
                          "model":  "stardewcraft:item/large_egg_brown_gold"
                      },
                      {
                          "predicate":  {
                                            "custom_model_data":  3
                                        },
                          "model":  "stardewcraft:item/large_egg_brown_iridium"
                      }
                  ]
}
