{
  "type": "minecraft:command",
  "pools": [
    {
      "rolls": 1,
      "entries": [
        {
          "type": "minecraft:item",
          "name": "minecraft:carrot_on_a_stick",
          "functions": [
            {
              "function": "minecraft:set_count",
              "count": 1
            },
            {
              "function": "minecraft:set_components",
              "components": {
                "minecraft:custom_model_data": 3001,
                "minecraft:max_stack_size": 99,
                "!minecraft:max_damage": {},
                "minecraft:custom_name": "{\"text\": \"熔炉\", \"color\": \"white\", \"italic\": false}",
                "minecraft:lore": [
                  "{\"text\": \"售价：\", \"color\": \"white\", \"italic\": false, \"extra\": [{\"text\": \"无法出售\", \"color\": \"red\"}]}",
                  "{\"text\": \"物品种类：\", \"color\": \"white\", \"italic\": false, \"extra\": [{\"text\": \"实用设施\", \"color\": \"gold\", \"bold\": true}]}",
                  "{\"text\": \"将矿石和煤炭转换为金属锭。\", \"color\": \"gray\", \"italic\": false}",
                  "{\"text\": \"\"}",
                  "{\"text\": \"右键放置\", \"color\": \"white\", \"italic\": false, \"extra\": [{\"text\": \"熔炉\", \"color\": \"green\", \"bold\": true}]}",
                  "{\"text\": \"放入\", \"color\": \"white\", \"italic\": false, \"extra\": [{\"text\": \"矿石和煤炭\", \"color\": \"green\", \"bold\": true}, {\"text\": \"进行冶炼\", \"color\": \"white\"}]}",
                  "{\"text\": \"用\", \"color\": \"white\", \"italic\": false, \"extra\": [{\"text\": \"镐子左键\", \"color\": \"green\", \"bold\": true}, {\"text\": \"可以拆除\", \"color\": \"white\"}]}"
                ],
                "minecraft:custom_data": {
                  "stardew_item": 1,
                  "utility_type": "furnace",
                  "item_category": "utility",
                  "placeable": 1
                }
              }
            }
          ]
        }
      ]
    }
  ]
}
