{
  "type": "minecraft:command",
  "pools": [
    {
      "rolls": 1,
      "entries": [
        {
          "type": "minecraft:item",
          "name": "minecraft:carrot_on_a_stick",
          "functions": [
            {
              "function": "minecraft:set_components",
              "components": {
                "minecraft:custom_model_data": 6100013,
                "minecraft:custom_name": "[{\"text\":\"淬火 \",\"color\":\"#A0522D\",\"bold\":true,\"italic\":false},{\"text\":\"阔剑\",\"color\":\"white\",\"bold\":true,\"italic\":false}]",
                "minecraft:attribute_modifiers": {
                  "modifiers": [
                    {
                      "type": "minecraft:attack_speed",
                      "id": "stardew:weapon_attack_speed",
                      "amount": -2.7,
                      "operation": "add_value",
                      "slot": "mainhand"
                    }
                  ],
                  "show_in_tooltip": false
                },
                "minecraft:lore": [
                  "{\"text\": \"📊 武器等级: \", \"color\": \"white\", \"italic\": false, \"extra\": [{\"text\": \"Lv.7\", \"color\": \"#FFD700\", \"bold\": true}]}",
                  "{\"text\": \"⚔ 战斗等级要求: \", \"color\": \"white\", \"italic\": false, \"extra\": [{\"text\": \"7\", \"color\": \"green\", \"bold\": true}]}",
                  "{\"text\":\"💥 伤害: \",\"color\":\"white\",\"italic\":false,\"extra\":[{\"text\":\"34-48\",\"color\":\"red\",\"bold\":true}]}",
                  "{\"text\":\"☆ 暴击率: \",\"color\":\"white\",\"italic\":false,\"extra\":[{\"text\":\"+2%\",\"color\":\"gold\",\"bold\":true}]}",
                  "{\"text\":\"⚡ 攻击速度: \",\"color\":\"white\",\"italic\":false,\"extra\":[{\"text\":\"1.3/秒\",\"color\":\"aqua\",\"bold\":true}]}",
                  "{\"text\":\"⚒ 技能: \",\"color\":\"white\",\"italic\":false,\"extra\":[{\"text\":\"格挡 III\",\"color\":\"light_purple\",\"bold\":true},{\"text\":\" (右键)\",\"color\":\"gray\",\"bold\":false}]}",
                  "{\"text\":\"⚒ 特殊技能: \",\"color\":\"white\",\"italic\":false,\"extra\":[{\"text\":\"旋风斩\",\"color\":\"#FF6347\",\"bold\":true},{\"text\":\" (Shift+右键)\",\"color\":\"gray\",\"bold\":false}]}",
                  "{\"text\": \"💰 售价：\", \"color\": \"white\", \"italic\": false, \"extra\": [{\"text\": \"无法出售\", \"color\": \"red\", \"bold\": true}]}",
                  "{\"text\": \"🔧 物品种类：\", \"color\": \"white\", \"italic\": false, \"extra\": [{\"text\": \"武器\", \"color\": \"red\", \"bold\": true}]}",
                  "{\"text\": \"🔨 经过精心回火的重型阔剑。\", \"color\": \"gray\", \"italic\": false}",
                  "{\"text\": \"🔨 兼具韧性与锋利。\", \"color\": \"dark_gray\", \"italic\": false}",
                  "{\"text\": \"\"}",
                  "{\"text\": \"技能 - \", \"color\": \"white\", \"italic\": false, \"extra\": [{\"text\": \"格挡 III\", \"color\": \"light_purple\", \"bold\": true}]}",
                  "{\"text\": \"▪ 效果: \", \"color\": \"gray\", \"italic\": false, \"extra\": [{\"text\": \"格挡期间减免70%伤害\", \"color\": \"white\", \"bold\": false}]}",
                  "{\"text\": \"▪ 持续时间: \", \"color\": \"gray\", \"italic\": false, \"extra\": [{\"text\": \"3.0秒\", \"color\": \"white\", \"bold\": false}]}",
                  "{\"text\": \"▪ 冷却时间: \", \"color\": \"gray\", \"italic\": false, \"extra\": [{\"text\": \"6.0秒\", \"color\": \"white\", \"bold\": false}]}",
                  "{\"text\": \"\"}",
                  "{\"text\": \"特殊技能 - \", \"color\": \"white\", \"italic\": false, \"extra\": [{\"text\": \"旋风斩\", \"color\": \"#FF6347\", \"bold\": true}]}",
                  "{\"text\": \"▪ 效果: \", \"color\": \"gray\", \"italic\": false, \"extra\": [{\"text\": \"360°范围攻击周围敌人\", \"color\": \"white\", \"bold\": false}]}",
                  "{\"text\": \"▪ 范围: \", \"color\": \"gray\", \"italic\": false, \"extra\": [{\"text\": \"3格半径\", \"color\": \"white\", \"bold\": false}]}",
                  "{\"text\": \"▪ 伤害: \", \"color\": \"gray\", \"italic\": false, \"extra\": [{\"text\": \"80%武器伤害\", \"color\": \"white\", \"bold\": false}]}",
                  "{\"text\": \"▪ 冷却时间: \", \"color\": \"gray\", \"italic\": false, \"extra\": [{\"text\": \"6.0秒\", \"color\": \"white\", \"bold\": false}]}"
                ],
                "minecraft:max_stack_size": 1,
                "minecraft:custom_data": {
                  "stardew_item": true,
                  "stardew_weapon": true,
                  "weapon_type": "sword",
                  "weapon_damage_min": 34,
                  "weapon_damage_max": 48,
                  "weapon_crit_chance": 0.02,
                  "weapon_attack_speed": 1.3,
                  "weapon_special": "block",
                  "weapon_special_2": "whirlwind",
                  "weapon_block_level": 3,
                  "weapon_skill_cooldown": 120,
                  "weapon_skill_2_cooldown": 120,
                  "weapon_level": 7
                }
              }
            }
          ]
        }
      ]
    }
  ]
}
