{
  "npc_id": "george",
  "_vanilla_ref": "Loved: 20=leek 205=fried_mushroom. Liked: 18=daffodil 195=sashimi? 199=parsnip_soup? 200=vegetable_medley 214=crispy_bass? 219=trout_soup? 223=cookie 231=eggplant_parmesan? 233=ice_cream. Disliked: -80=flower_category 16=horseradish?. Hated: 22=dandelion? 80=quartz 330=clay.",
  "loved": [
    "stardewcraft:leek",
    "stardewcraft:fried_mushroom"
  ],
  "liked": [
    "stardewcraft:daffodil",
    "stardewcraft:omelet",
    "stardewcraft:parsnip_soup",
    "stardewcraft:vegetable_medley",
    "stardewcraft:crispy_bass",
    "stardewcraft:trout_soup",
    "stardewcraft:cookie",
    "stardewcraft:eggplant_parmesan",
    "stardewcraft:ice_cream"
  ],
  "neutral": [],
  "disliked": [
    "stardewcraft:wild_horseradish",
    "stardewcraft:sweet_pea",
    "stardewcraft:crocus",
    "stardewcraft:sunflower",
    "stardewcraft:tulip",
    "stardewcraft:summer_spangle",
    "stardewcraft:fairy_rose",
    "stardewcraft:blue_jazz",
    "stardewcraft:poppy"
  ],
  "_disliked_not_yet_in_mod": [
    "flower_category(-80)"
  ],
  "hated": [
    "stardewcraft:dandelion",
    "stardewcraft:quartz",
    "stardewcraft:clay"
  ],
  "loved_msg": "Well, well... this is a very fine gift! Thank you.",
  "liked_msg": "Hmmph... okay, this is actually pretty nice. Thanks.",
  "neutral_msg": "Hmmph. Thanks, I guess.",
  "disliked_msg": "What am I supposed to do with this? Hmmph.",
  "hated_msg": "What?! This is awful! Get this away from me!"
}
